{"1":{"id":1,"client_id":-1,"client_firstname":"kd","client_lastname":"k","client_email":"k@k","freelancer_id":1,"freelancer_firstname":"Brian","freelancer_lastname":"Fu","name":"k","contract":"","amount":100000,"milestones":[{"date":"2019-03-19","amount":100000,"description":"deposit","feedback":"","client_approved":false,"freelancer_approved":true}]},"2":{"id":2,"client_id":-1,"client_firstname":"Kitty","client_lastname":"Cat","client_email":"cats@gmail.com","freelancer_id":1,"freelancer_firstname":"Brian","freelancer_lastname":"Fu","name":"Catnip dispenser","contract":"","amount":80000,"milestones":[{"date":"","amount":80000,"description":"","feedback":"","client_approved":false,"freelancer_approved":true}]},"3":{"id":3,"client_id":-1,"client_firstname":"Elon","client_lastname":"Musk","client_email":"elon@gmail.com","freelancer_id":1,"freelancer_firstname":"Brian","freelancer_lastname":"Fu","name":"Brand Strategy Memo","contract":"","amount":40000,"milestones":[{"date":"2019-03-30","amount":40000,"description":"Make cola","feedback":"","client_approved":false,"freelancer_approved":true}]},"4":{"id":4,"client_id":-1,"client_firstname":"Add","client_lastname":"Project","client_email":"add@project.com","freelancer_id":1,"freelancer_firstname":"Brian","freelancer_lastname":"Fu","name":"Dog food","contract":"","amount":89888,"milestones":[{"date":"2019-03-27","amount":89888,"description":"Buy whole foods","feedback":"","client_approved":false,"freelancer_approved":true}]},"5":{"id":5,"client_id":-1,"client_firstname":"Baseball","client_lastname":"Coach","client_email":"bucks@milwaukee.com","freelancer_id":1,"freelancer_firstname":"Brian","freelancer_lastname":"Fu","name":"Baseball Bats","contract":"","amount":24200,"milestones":[{"date":"2019-03-19","amount":24200,"description":"Make bats","feedback":"","client_approved":false,"freelancer_approved":true}]},"6":{"id":6,"client_id":-1,"client_firstname":"Final","client_lastname":"Countdown","client_email":"final@countdown.com","freelancer_id":1,"freelancer_firstname":"Brian","freelancer_lastname":"Fu","name":"Song","contract":"","amount":50000,"milestones":[{"date":"2019-03-19","amount":25000,"description":"vocals","feedback":"","client_approved":false,"freelancer_approved":true},{"date":"2019-03-30","amount":25000,"description":"soundtrack","feedback":"","client_approved":false,"freelancer_approved":true}]},"7":{"id":7,"client_id":-1,"client_firstname":"Jordan","client_lastname":"Chernof","client_email":"jordan.chernof@gmail.com","freelancer_id":1,"freelancer_firstname":"Brian","freelancer_lastname":"Fu","name":"Br","contract":"","amount":20000,"milestones":[{"date":"2019-03-21","amount":20000,"description":"Create amazon echo","feedback":"","client_approved":false,"freelancer_approved":false},{"date":"","amount":20000,"description":"","feedback":"","client_approved":false,"freelancer_approved":false}]}}